salmagundi/__init__.py
salmagundi/_docopt.py
salmagundi/_stopwatch.py
salmagundi/colors.py
salmagundi/files.py
salmagundi/inputs.py
salmagundi/strings.py
salmagundi/utils.py
salmagundi/validation.py
salmagundi-0.17.1.dist-info/LICENSE.txt
salmagundi-0.17.1.dist-info/METADATA
salmagundi-0.17.1.dist-info/WHEEL
salmagundi-0.17.1.dist-info/top_level.txt
salmagundi-0.17.1.dist-info/RECORD
