Metadata-Version: 2.1
Name: salmagundi
Version: 0.17.1
Summary: Library with a collection of some more or less useful functions.
Home-page: https://andreas19.github.io/salmagundi/
Author: Andreas Suhre
Author-email: andreas19@posteo.eu
License: BSD-3-Clause
Project-URL: Source code, https://github.com/andreas19/salmagundi/
Keywords: files,strings,console,terminal,input,menu,utils,utilities
Platform: UNKNOWN
Classifier: Development Status :: 4 - Beta
Classifier: Intended Audience :: Developers
Classifier: License :: OSI Approved :: BSD License
Classifier: Natural Language :: English
Classifier: Operating System :: OS Independent
Classifier: Programming Language :: Python :: 3
Classifier: Programming Language :: Python :: 3.6
Classifier: Programming Language :: Python :: 3.7
Classifier: Programming Language :: Python :: 3.8
Classifier: Programming Language :: Python :: 3.9
Classifier: Topic :: Software Development :: Libraries
Requires-Python: >=3.6
License-File: LICENSE.txt
Requires-Dist: wcwidth (>=0.2.5)
